{
  "criticality_counts": {
    "critical": 1021,
    "high": 55,
    "leaf": 792,
    "medium": 300
  },
  "flagship_signal_used": false,
  "node_count": 2168,
  "thresholds": {
    "critical_descendants": 250,
    "critical_in_degree": 15,
    "high_descendants": 100,
    "high_in_degree": 5,
    "medium_descendants": 5,
    "medium_in_degree": 2
  },
  "top_25_by_load_bearing_score": [
    {
      "claim_id": "minimal_axioms_2026-05-03",
      "criticality": "critical",
      "load_bearing_score": 82.809,
      "transitive_descendants": 896
    },
    {
      "claim_id": "staggered_dirac_realization_gate_note_2026-05-03",
      "criticality": "critical",
      "load_bearing_score": 43.26,
      "transitive_descendants": 866
    },
    {
      "claim_id": "three_generation_observable_theorem_note",
      "criticality": "critical",
      "load_bearing_score": 42.248,
      "transitive_descendants": 429
    },
    {
      "claim_id": "observable_principle_from_axiom_note",
      "criticality": "critical",
      "load_bearing_score": 41.162,
      "transitive_descendants": 572
    },
    {
      "claim_id": "graph_first_su3_integration_note",
      "criticality": "critical",
      "load_bearing_score": 39.241,
      "transitive_descendants": 855
    },
    {
      "claim_id": "minimal_axioms_2026-04-11",
      "criticality": "critical",
      "load_bearing_score": 37.064,
      "transitive_descendants": 756
    },
    {
      "claim_id": "alpha_s_derived_note",
      "criticality": "critical",
      "load_bearing_score": 35.642,
      "transitive_descendants": 564
    },
    {
      "claim_id": "staggered_dirac_substep4_ac_narrow_bounded_note_2026-05-07_substep4ac",
      "criticality": "critical",
      "load_bearing_score": 34.089,
      "transitive_descendants": 384
    },
    {
      "claim_id": "yt_ward_identity_derivation_theorem",
      "criticality": "critical",
      "load_bearing_score": 32.823,
      "transitive_descendants": 452
    },
    {
      "claim_id": "native_gauge_closure_note",
      "criticality": "critical",
      "load_bearing_score": 32.218,
      "transitive_descendants": 841
    },
    {
      "claim_id": "ckm_cp_phase_structural_identity_theorem_note_2026-04-24",
      "criticality": "critical",
      "load_bearing_score": 31.364,
      "transitive_descendants": 465
    },
    {
      "claim_id": "koide_circulant_character_derivation_note_2026-04-18",
      "criticality": "critical",
      "load_bearing_score": 30.589,
      "transitive_descendants": 384
    },
    {
      "claim_id": "yt_ew_color_projection_theorem",
      "criticality": "critical",
      "load_bearing_score": 30.483,
      "transitive_descendants": 505
    },
    {
      "claim_id": "anomaly_forces_time_theorem",
      "criticality": "critical",
      "load_bearing_score": 30.416,
      "transitive_descendants": 682
    },
    {
      "claim_id": "wolfenstein_lambda_a_structural_identities_theorem_note_2026-04-24",
      "criticality": "critical",
      "load_bearing_score": 30.358,
      "transitive_descendants": 463
    },
    {
      "claim_id": "left_handed_charge_matching_note",
      "criticality": "critical",
      "load_bearing_score": 27.748,
      "transitive_descendants": 607
    },
    {
      "claim_id": "three_generation_structure_note",
      "criticality": "critical",
      "load_bearing_score": 27.619,
      "transitive_descendants": 555
    },
    {
      "claim_id": "charged_lepton_koide_cone_algebraic_equivalence_note",
      "criticality": "critical",
      "load_bearing_score": 27.089,
      "transitive_descendants": 384
    },
    {
      "claim_id": "dm_neutrino_source_surface_active_half_plane_theorem_note_2026-04-16",
      "criticality": "critical",
      "load_bearing_score": 27.089,
      "transitive_descendants": 384
    },
    {
      "claim_id": "ckm_magnitudes_structural_counts_theorem_note_2026-04-25",
      "criticality": "critical",
      "load_bearing_score": 26.827,
      "transitive_descendants": 453
    },
    {
      "claim_id": "standard_model_hypercharge_uniqueness_theorem_note_2026-04-24",
      "criticality": "critical",
      "load_bearing_score": 26.457,
      "transitive_descendants": 496
    },
    {
      "claim_id": "ckm_atlas_axiom_closure_note",
      "criticality": "critical",
      "load_bearing_score": 25.96,
      "transitive_descendants": 497
    },
    {
      "claim_id": "plaquette_self_consistency_note",
      "criticality": "critical",
      "load_bearing_score": 25.757,
      "transitive_descendants": 611
    },
    {
      "claim_id": "staggered_dirac_bz_corner_forcing_theorem_note_2026-05-07",
      "criticality": "critical",
      "load_bearing_score": 25.611,
      "transitive_descendants": 390
    },
    {
      "claim_id": "cl3_color_automorphism_theorem",
      "criticality": "critical",
      "load_bearing_score": 25.306,
      "transitive_descendants": 632
    }
  ]
}
