{
  "criticality_counts": {
    "critical": 1024,
    "high": 53,
    "leaf": 744,
    "medium": 294
  },
  "flagship_signal_used": false,
  "node_count": 2115,
  "thresholds": {
    "critical_descendants": 250,
    "critical_in_degree": 15,
    "high_descendants": 100,
    "high_in_degree": 5,
    "medium_descendants": 5,
    "medium_in_degree": 2
  },
  "top_25_by_load_bearing_score": [
    {
      "claim_id": "minimal_axioms_2026-05-03",
      "criticality": "critical",
      "load_bearing_score": 78.273,
      "transitive_descendants": 874
    },
    {
      "claim_id": "staggered_dirac_realization_gate_note_2026-05-03",
      "criticality": "critical",
      "load_bearing_score": 42.225,
      "transitive_descendants": 845
    },
    {
      "claim_id": "three_generation_observable_theorem_note",
      "criticality": "critical",
      "load_bearing_score": 41.275,
      "transitive_descendants": 437
    },
    {
      "claim_id": "observable_principle_from_axiom_note",
      "criticality": "critical",
      "load_bearing_score": 39.124,
      "transitive_descendants": 557
    },
    {
      "claim_id": "graph_first_su3_integration_note",
      "criticality": "critical",
      "load_bearing_score": 38.204,
      "transitive_descendants": 833
    },
    {
      "claim_id": "minimal_axioms_2026-04-11",
      "criticality": "critical",
      "load_bearing_score": 37.057,
      "transitive_descendants": 752
    },
    {
      "claim_id": "alpha_s_derived_note",
      "criticality": "critical",
      "load_bearing_score": 35.129,
      "transitive_descendants": 559
    },
    {
      "claim_id": "staggered_dirac_substep4_ac_narrow_bounded_note_2026-05-07_substep4ac",
      "criticality": "critical",
      "load_bearing_score": 33.043,
      "transitive_descendants": 372
    },
    {
      "claim_id": "ckm_cp_phase_structural_identity_theorem_note_2026-04-24",
      "criticality": "critical",
      "load_bearing_score": 31.327,
      "transitive_descendants": 453
    },
    {
      "claim_id": "yt_ward_identity_derivation_theorem",
      "criticality": "critical",
      "load_bearing_score": 31.307,
      "transitive_descendants": 447
    },
    {
      "claim_id": "native_gauge_closure_note",
      "criticality": "critical",
      "load_bearing_score": 31.181,
      "transitive_descendants": 820
    },
    {
      "claim_id": "anomaly_forces_time_theorem",
      "criticality": "critical",
      "load_bearing_score": 30.386,
      "transitive_descendants": 668
    },
    {
      "claim_id": "wolfenstein_lambda_a_structural_identities_theorem_note_2026-04-24",
      "criticality": "critical",
      "load_bearing_score": 30.32,
      "transitive_descendants": 451
    },
    {
      "claim_id": "koide_circulant_character_derivation_note_2026-04-18",
      "criticality": "critical",
      "load_bearing_score": 29.543,
      "transitive_descendants": 372
    },
    {
      "claim_id": "yt_ew_color_projection_theorem",
      "criticality": "critical",
      "load_bearing_score": 29.431,
      "transitive_descendants": 487
    },
    {
      "claim_id": "three_generation_structure_note",
      "criticality": "critical",
      "load_bearing_score": 27.582,
      "transitive_descendants": 541
    },
    {
      "claim_id": "left_handed_charge_matching_note",
      "criticality": "critical",
      "load_bearing_score": 27.234,
      "transitive_descendants": 601
    },
    {
      "claim_id": "charged_lepton_koide_cone_algebraic_equivalence_note",
      "criticality": "critical",
      "load_bearing_score": 27.043,
      "transitive_descendants": 372
    },
    {
      "claim_id": "dm_neutrino_source_surface_active_half_plane_theorem_note_2026-04-16",
      "criticality": "critical",
      "load_bearing_score": 27.043,
      "transitive_descendants": 372
    },
    {
      "claim_id": "ckm_magnitudes_structural_counts_theorem_note_2026-04-25",
      "criticality": "critical",
      "load_bearing_score": 26.788,
      "transitive_descendants": 441
    },
    {
      "claim_id": "ckm_atlas_axiom_closure_note",
      "criticality": "critical",
      "load_bearing_score": 25.925,
      "transitive_descendants": 485
    },
    {
      "claim_id": "standard_model_hypercharge_uniqueness_theorem_note_2026-04-24",
      "criticality": "critical",
      "load_bearing_score": 25.919,
      "transitive_descendants": 483
    },
    {
      "claim_id": "cl3_color_automorphism_theorem",
      "criticality": "critical",
      "load_bearing_score": 25.29,
      "transitive_descendants": 625
    },
    {
      "claim_id": "plaquette_self_consistency_note",
      "criticality": "critical",
      "load_bearing_score": 25.241,
      "transitive_descendants": 604
    },
    {
      "claim_id": "staggered_dirac_bz_corner_forcing_theorem_note_2026-05-07",
      "criticality": "critical",
      "load_bearing_score": 24.651,
      "transitive_descendants": 401
    }
  ]
}
