{
  "computed_at": "2026-05-12T00:58:49.272617+00:00",
  "criticality_counts": {
    "critical": 73,
    "high": 336,
    "leaf": 1267,
    "medium": 450
  },
  "flagship_signal_used": false,
  "node_count": 2126,
  "thresholds": {
    "critical_descendants": 250,
    "critical_in_degree": 15,
    "high_descendants": 100,
    "high_in_degree": 5,
    "medium_descendants": 5,
    "medium_in_degree": 2
  },
  "top_25_by_load_bearing_score": [
    {
      "claim_id": "alpha_s_derived_note",
      "criticality": "critical",
      "load_bearing_score": 29.46,
      "transitive_descendants": 248
    },
    {
      "claim_id": "wolfenstein_lambda_a_structural_identities_theorem_note_2026-04-24",
      "criticality": "critical",
      "load_bearing_score": 28.858,
      "transitive_descendants": 115
    },
    {
      "claim_id": "ckm_cp_phase_structural_identity_theorem_note_2026-04-24",
      "criticality": "critical",
      "load_bearing_score": 28.845,
      "transitive_descendants": 114
    },
    {
      "claim_id": "graph_first_su3_integration_note",
      "criticality": "critical",
      "load_bearing_score": 28.219,
      "transitive_descendants": 297
    },
    {
      "claim_id": "yt_ward_identity_derivation_theorem",
      "criticality": "critical",
      "load_bearing_score": 27.714,
      "transitive_descendants": 296
    },
    {
      "claim_id": "observable_principle_from_axiom_note",
      "criticality": "critical",
      "load_bearing_score": 26.901,
      "transitive_descendants": 238
    },
    {
      "claim_id": "ckm_magnitudes_structural_counts_theorem_note_2026-04-25",
      "criticality": "critical",
      "load_bearing_score": 23.672,
      "transitive_descendants": 101
    },
    {
      "claim_id": "yt_ew_color_projection_theorem",
      "criticality": "critical",
      "load_bearing_score": 22.383,
      "transitive_descendants": 117
    },
    {
      "claim_id": "three_generation_observable_theorem_note",
      "criticality": "critical",
      "load_bearing_score": 21.665,
      "transitive_descendants": 286
    },
    {
      "claim_id": "three_generation_structure_note",
      "criticality": "critical",
      "load_bearing_score": 20.972,
      "transitive_descendants": 250
    },
    {
      "claim_id": "ckm_atlas_triangle_right_angle_theorem_note_2026-04-24",
      "criticality": "critical",
      "load_bearing_score": 20.833,
      "transitive_descendants": 113
    },
    {
      "claim_id": "one_generation_matter_closure_note",
      "criticality": "critical",
      "load_bearing_score": 20.437,
      "transitive_descendants": 244
    },
    {
      "claim_id": "ckm_nlo_barred_triangle_protected_gamma_theorem_note_2026-04-25",
      "criticality": "critical",
      "load_bearing_score": 19.555,
      "transitive_descendants": 93
    },
    {
      "claim_id": "minimal_axioms_2026-04-11",
      "criticality": "critical",
      "load_bearing_score": 18.794,
      "transitive_descendants": 110
    },
    {
      "claim_id": "planck_parent_source_hidden_character_no_go_note_2026-04-24",
      "criticality": "high",
      "load_bearing_score": 18.426,
      "transitive_descendants": 42
    },
    {
      "claim_id": "left_handed_charge_matching_note",
      "criticality": "critical",
      "load_bearing_score": 17.477,
      "transitive_descendants": 251
    },
    {
      "claim_id": "anomaly_forces_time_theorem",
      "criticality": "critical",
      "load_bearing_score": 17.454,
      "transitive_descendants": 247
    },
    {
      "claim_id": "ckm_atlas_axiom_closure_note",
      "criticality": "critical",
      "load_bearing_score": 17.229,
      "transitive_descendants": 74
    },
    {
      "claim_id": "native_gauge_closure_note",
      "criticality": "critical",
      "load_bearing_score": 16.7,
      "transitive_descendants": 293
    },
    {
      "claim_id": "r_base_group_theory_derivation_theorem_note_2026-04-24",
      "criticality": "critical",
      "load_bearing_score": 16.419,
      "transitive_descendants": 120
    },
    {
      "claim_id": "plaquette_self_consistency_note",
      "criticality": "critical",
      "load_bearing_score": 16.229,
      "transitive_descendants": 299
    },
    {
      "claim_id": "physical_lattice_necessity_note",
      "criticality": "critical",
      "load_bearing_score": 16.145,
      "transitive_descendants": 282
    },
    {
      "claim_id": "dm_neutrino_source_surface_active_half_plane_theorem_note_2026-04-16",
      "criticality": "critical",
      "load_bearing_score": 15.5,
      "transitive_descendants": 127
    },
    {
      "claim_id": "site_phase_cube_shift_intertwiner_note",
      "criticality": "critical",
      "load_bearing_score": 15.18,
      "transitive_descendants": 289
    },
    {
      "claim_id": "cosmological_constant_spectral_gap_identity_theorem_note",
      "criticality": "critical",
      "load_bearing_score": 15.115,
      "transitive_descendants": 48
    }
  ]
}
