{
  "alpha_s_MZ_claimed": false,
  "benchmark": {
    "acceptance_rate": 0.152,
    "beta": 6.0,
    "measured_volume": "12^3x24",
    "seconds_per_sweep": 14.181,
    "seconds_per_updated_link": 8.549e-05,
    "updated_links_per_sweep": 165888
  },
  "certificate_generated": false,
  "compiled_or_jit_options": {
    "Cython": "unavailable",
    "clang": "available",
    "cffi": "available",
    "cupy": "unavailable",
    "meson": "unavailable",
    "numba": "installed during follow-up; backend added but benchmark gate failed",
    "pybind11": "unavailable"
  },
  "compiled_numba_attempt": {
    "backend": "scripts/alpha_s_numba_wilson_loop_mc.py",
    "benchmark_report": "outputs/alpha_s_wilson_loop_production/COMPILED_MC_NUMBA_BENCHMARK_REPORT_2026-04-30.md",
    "benchmarks": {
      "4^4_heatbath_only": {
        "compiled_us_per_link": 4.503118907450698,
        "speedup_target_pass": false,
        "speedup_vs_pure_python_heatbath": 40.52746635183052
      },
      "8^3x16_heatbath_only": {
        "compiled_us_per_link": 5.446027564914857,
        "speedup_target_pass": false,
        "speedup_vs_pure_python_heatbath": 33.5106640252294
      },
      "8^4_heatbath_only_100_sweeps": {
        "compiled_us_per_link": 5.204889984042893,
        "speedup_target_pass": false,
        "speedup_vs_pure_python_heatbath": 35.06318107769942
      },
      "8^4_heatbath_plus_4_overrelax": {
        "compiled_us_per_link": 22.257915750856228,
        "plaquette_diagnostic": 0.0019473394829080057,
        "production_valid": false,
        "speedup_target_pass": false,
        "speedup_vs_pure_python_heatbath": 8.199330163830794
      }
    },
    "compiled_inner_loops": [
      "SU(3) matmul/dagger/projection helpers",
      "Cabibbo-Marinari SU(2)-subgroup heat-bath update",
      "SU(2)-subgroup overrelaxation update",
      "staple sum",
      "plaquette",
      "APE spatial smearing",
      "rectangular Wilson-loop measurement"
    ],
    "conclusion": "compiled backend exists but does not meet the 50x speed gate; overrelaxation path is not production-valid"
  },
  "date": "2026-04-30",
  "estimated_sweep_only_wall_time_days": {
    "12^3x24": 3.4,
    "16^3x32": 10.9,
    "24^3x48": 55.1,
    "total": 69.4
  },
  "excluded_from_estimate": [
    "Wilson-loop measurement overhead for R,T=1..8",
    "APE/HYP smearing",
    "jackknife/bootstrap analysis",
    "static-potential plateau fitting",
    "reruns for autocorrelation or failed plateaus"
  ],
  "existing_infrastructure": [
    "scripts/frontier_alpha_s_direct_wilson_loop.py",
    "scripts/frontier_plaquette_self_consistency.py",
    "scripts/frontier_g_bare_critical_feature_scan.py",
    "scripts/frontier_confinement_string_tension.py",
    "scripts/frontier_color_projection_mc.py"
  ],
  "existing_pure_python_heatbath_benchmark": {
    "4^4": {
      "plaquette_after_one_sweep": 0.6969,
      "seconds_per_sweep": 0.177,
      "seconds_per_updated_link": 0.0001724
    },
    "6^4": {
      "plaquette_after_one_sweep": 0.6989,
      "seconds_per_sweep": 0.975,
      "seconds_per_updated_link": 0.0001881
    },
    "8^4": {
      "plaquette_after_one_sweep": 0.6988,
      "seconds_per_sweep": 2.991,
      "seconds_per_updated_link": 0.0001825
    },
    "source": "scripts/frontier_color_projection_mc.py"
  },
  "missing_production_features": [
    "validated >=50x compiled Cabibbo-Marinari heat-bath kernel",
    "production-valid SU(3) overrelaxation sweeps",
    "autocorrelation analysis",
    "production Wilson-loop/static-potential certificate",
    "full production uncertainty budget"
  ],
  "phase2_status": "blocked",
  "reason": "Existing repo SU(3) Wilson MC infrastructure was pure Python; a numba backend was added, but it failed the requested 50x speed gate and the overrelaxation diagnostic is not production-valid.",
  "requested_protocol": {
    "measurement_separation_sweeps": 20,
    "measurements_per_volume": 1000,
    "thermalization_sweeps": 1000,
    "volumes": [
      "12^3x24",
      "16^3x32",
      "24^3x48"
    ]
  },
  "strict_runner_expected_result": "blocked_missing_production_certificate"
}
